{
    "Home": "Ana səhifə",
    "Planes": "Təyyarələr",
    "Airlines": "Avialaynerlər",
    "Adminstrators": "İnzibatçılar",
    "Flights": "Uçuşlar",
    "Flights tickets": "Uçuş biletləri",
    "Passengers": "Sərnişinlər",
    "Exit": "Çıxış",
    "welcome": "Sistəmə xoş gəldiniz!",
    "amount": "Balans",
    "add": "Əlavə et",
    "edit": "Düzəlt",
    "delete": "Sil",
    "save": "Saxla",
    "cancel": "Ləğv et",
    "country": "Ölkə",
    "username": "İstifadəçi adı",
    "password": "Şifrə",
    "email": "E-poçt",
    "birthDate": "Doğum tarixi",
    "from": "Haradan",
    "to": "Haraya",
    "gates": "Qapılar",
    "actions": "Əməliyyatlar",
    "pilot": "Pilot",
    "model": "Model",
    "type": "Növ",
    "baggagePrice":"Baqaj qiyməti",
    "ecoCapacity": "Ekonom sinif kontinenti",
    "busCapacity": "Biznes sinif kontinenti",
    "baggageCap": "Bağlama kapasiteti",
    "currentStatus": "Cari vəziyyət",
    "ticketCount": "Bilet sayı",
    "soldTicket": "Satılmış bilet",
    "passengerName": "Sərnişin adı",
    "passengerLastName": "Sərnişin soyadı",
    "passengerBirthDate": "Sərnişin doğum tarixi",
    "passengerN": "Sərnişin nömrəsi",
    "passportCountry": "Pasport ölkəsi",
    "passportExpireDate": "Pasportun bitmə tarixi",
    "passportNumber": "Pasport nömrəsi",
    "warningLabel": "Səhifə tapılmadı, xahiş edirik başqa səhifəyə yönləndirin",
    "departureTime": "Hərəkət vaxtı",
    "landingTime": "Eniş vaxtı",
    "price": "Qiymət",
    "airline": "Avialayn",
    "plane": "Təyyarə",
    "firstName": "Ad",
    "lastName": "Soyad",
    "flight": "Uçuş",
    "ticket": "Bilet",
    "title": "Başlıq",
    "ticketNumber": "Bilet nömrəsi",
    "search": "Axtarış",
    "flightNumber": "Uçuş nömrəsi",
    "flightDate": "Uçuş tarixi",
    "flightTime": "Uçuş vaxtı",
    "flightAirline": "Uçuşun aviaşirkəti",
    "arrivalDate": "Gələcək tarix",
    "arrivalTime": "Gələcək vaxt",
    "arrivalAirline": "Gələcək aviaşirkət",
    "finish":"Bitir",
    "selectCountry":"Ölkə seç",
    "areusure":"Əminsiniz mi?",
    "yes": "Bəli",
    "no": "Xeyr",
    "success": "Uğur!",
    "nosuccess": "Heç bir dəyişlik baş tutmadı!"
  }
  